MANIFEST.in
README.rst
setup.py
django_pronouns/__init__.py
django_pronouns/admin.py
django_pronouns/models.py
django_pronouns.egg-info/PKG-INFO
django_pronouns.egg-info/SOURCES.txt
django_pronouns.egg-info/dependency_links.txt
django_pronouns.egg-info/top_level.txt
django_pronouns/fixtures/pronouns.json
django_pronouns/migrations/0001_initial.py
django_pronouns/migrations/__init__.py