Metadata-Version: 1.1
Name: django-pronouns
Version: 0.3.0
Summary: Generic pronoun handling for Django applications
Home-page: https://bitbucket.org/tim_heap/django-pronouns
Author: Tim Heap
Author-email: tim@timheap.me
License: UNKNOWN
Platform: UNKNOWN
Classifier: Environment :: Web Environment
Classifier: Intended Audience :: Developers
Classifier: Operating System :: OS Independent
Classifier: Programming Language :: Python
Classifier: Programming Language :: Python :: 2
Classifier: Programming Language :: Python :: 2.7
Classifier: Programming Language :: Python :: 3
Classifier: Framework :: Django
